{
  "project_info": {
    "project_number": "181396098446",
    "firebase_url": "https://todoapp-eac35.firebaseio.com",
    "project_id": "todoapp-eac35",
    "storage_bucket": "todoapp-eac35.appspot.com"
  },
  "client": [
    {
      "client_info": {
        "mobilesdk_app_id": "1:181396098446:android:031b6dac2f3c2427",
        "android_client_info": {
          "package_name": "eu.artouch.todoapp"
        }
      },
      "oauth_client": [
        {
          "client_id": "181396098446-tsml6mtodikljjd8dnp4ejmj80oml369.apps.googleusercontent.com",
          "client_type": 1,
          "android_info": {
            "package_name": "eu.artouch.todoapp",
            "certificate_hash": "3b3df3d50fb989c49abadae5090db66a759d2cab"
          }
        },
        {
          "client_id": "181396098446-abgoioljdqdtun4kjsch2pu42a6pl240.apps.googleusercontent.com",
          "client_type": 3
        }
      ],
      "api_key": [
        {
          "current_key": "AIzaSyAmKN12T8i8iyICcrS5-IEsE71IyHw-aRY"
        }
      ],
      "services": {
        "analytics_service": {
          "status": 1
        },
        "appinvite_service": {
          "status": 2,
          "other_platform_oauth_client": [
            {
              "client_id": "181396098446-abgoioljdqdtun4kjsch2pu42a6pl240.apps.googleusercontent.com",
              "client_type": 3
            }
          ]
        },
        "ads_service": {
          "status": 2
        }
      }
    }
  ],
  "configuration_version": "1"
}